aiochannel/__init__.py
aiochannel/channel.py
aiochannel/errors.py
aiochannel/py.typed
aiochannel-1.3.0.dist-info/METADATA
aiochannel-1.3.0.dist-info/WHEEL
aiochannel-1.3.0.dist-info/RECORD
