Metadata-Version: 2.1
Name: aiochannel
Version: 1.3.0
Summary: asyncio Channels (closable queues) inspired by golang
Home-page: https://github.com/tbug/aiochannel
License: Apache-2.0
Keywords: asyncio,aio,chan,channel,gochan
Author: Henrik Tudborg
Author-email: henrik@tudb.org
Requires-Python: >=3.9,<4.0
Classifier: Development Status :: 5 - Production/Stable
Classifier: Framework :: AsyncIO
Classifier: Intended Audience :: Developers
Classifier: Intended Audience :: System Administrators
Classifier: License :: OSI Approved :: Apache Software License
Classifier: Natural Language :: English
Classifier: Operating System :: MacOS :: MacOS X
Classifier: Operating System :: Microsoft :: Windows
Classifier: Operating System :: POSIX
Classifier: Programming Language :: Python :: 3
Classifier: Programming Language :: Python :: 3.9
Classifier: Programming Language :: Python :: 3.10
Classifier: Programming Language :: Python :: 3.11
Classifier: Programming Language :: Python :: 3.12
Classifier: Programming Language :: Python :: 3.13
Classifier: Programming Language :: Python :: 3 :: Only
Classifier: Typing :: Typed
Project-URL: Source, https://github.com/tbug/aiochannel
Project-URL: Tracker, https://github.com/tbug/aiochannel/issues
